LIWCtools/LIWCtools.py
LIWCtools/__init__.py
LIWCtools/dictionarymatch-2001-2007.csv
LIWCtools-0.1.3.3.dist-info/DESCRIPTION.rst
LIWCtools-0.1.3.3.dist-info/METADATA
LIWCtools-0.1.3.3.dist-info/RECORD
LIWCtools-0.1.3.3.dist-info/WHEEL
LIWCtools-0.1.3.3.dist-info/metadata.json
LIWCtools-0.1.3.3.dist-info/top_level.txt
