Metadata-Version: 2.0
Name: LIWCtools
Version: 0.1.3.3
Summary: Tools for working with LIWC dictionaries
Home-page: https://github.com/pboot/liwctools
Author: Peter Boot
Author-email: pb@peterboot.nl
License: MIT
Provides-Extra: count
Requires-Dist: chardet; extra == 'count'
